pqcli/__init__.py
pqcli/__main__.py
pqcli/config.py
pqcli/lingo.py
pqcli/mechanic.py
pqcli/random.py
pqcli/roster.py
pqcli/ui/__init__.py
pqcli/ui/base.py
pqcli/ui/basic/__init__.py
pqcli/ui/curses/__init__.py
pqcli/ui/curses/colors.py
pqcli/ui/curses/event_handler.py
pqcli/ui/curses/util.py
pqcli/ui/curses/views/__init__.py
pqcli/ui/curses/views/base_view.py
pqcli/ui/curses/views/choose_character_view.py
pqcli/ui/curses/views/confirm_view.py
pqcli/ui/curses/views/menu_view.py
pqcli/ui/curses/views/roster_view.py
pqcli/ui/curses/views/create_character_view/__init__.py
pqcli/ui/curses/views/create_character_view/choose_character_class_view.py
pqcli/ui/curses/views/create_character_view/choose_character_name_view.py
pqcli/ui/curses/views/create_character_view/choose_character_race_view.py
pqcli/ui/curses/views/create_character_view/choose_character_stats_view.py
pqcli/ui/curses/views/game_view/__init__.py
pqcli/ui/curses/views/game_view/character_sheet_window.py
pqcli/ui/curses/views/game_view/equipment_window.py
pqcli/ui/curses/views/game_view/inventory_window.py
pqcli/ui/curses/views/game_view/plot_window.py
pqcli/ui/curses/views/game_view/progress_bar_window.py
pqcli/ui/curses/views/game_view/quest_book_window.py
pqcli/ui/curses/views/game_view/spell_book_window.py
pqcli/ui/curses/views/game_view/task_progress_window.py
pqcli/ui/curses/widgets/__init__.py
pqcli/ui/curses/widgets/base.py
pqcli/ui/curses/widgets/data_table.py
pqcli/ui/curses/widgets/focusable.py
pqcli/ui/curses/widgets/label.py
pqcli/ui/curses/widgets/list_box.py
pqcli/ui/curses/widgets/menu.py
pqcli/ui/curses/widgets/progress_bar.py
pqcli/ui/curses/widgets/scrollable.py
pqcli-1.0.4.dist-info/METADATA
pqcli-1.0.4.dist-info/WHEEL
pqcli-1.0.4.dist-info/entry_points.txt
pqcli-1.0.4.dist-info/licenses/LICENSE.md
pqcli-1.0.4.dist-info/RECORD
