Metadata-Version: 2.4
Name: pqcli
Version: 1.0.4
Summary: Progress Quest: the CLI edition
Project-URL: Repository, https://github.com/rr-/pq-cli.git
Author-email: Laura Kurczewska <dash@wind.garden>
License-Expression: MIT
License-File: LICENSE.md
Classifier: Development Status :: 4 - Beta
Classifier: Environment :: Console
Classifier: Intended Audience :: End Users/Desktop
Classifier: License :: OSI Approved :: MIT License
Classifier: Natural Language :: English
Classifier: Operating System :: POSIX :: Linux
Classifier: Programming Language :: Python :: 3 :: Only
Classifier: Programming Language :: Python :: 3.10
Classifier: Topic :: Games/Entertainment :: Role-Playing
Classifier: Topic :: Games/Entertainment :: Simulation
Requires-Python: <4.0,>=3.10
Requires-Dist: urwid-readline<1.0.0,>=0.13
Requires-Dist: urwid<3.0.0,>=2.1.2
Requires-Dist: xdg-base-dirs<7.0.0,>=6.0.0
Provides-Extra: windows
Requires-Dist: windows-curses<3.0.0,>=2.3.0; extra == 'windows'
